wmsan/__init__.py
wmsan/read_hs_p2l.py
wmsan/subfunctions_body_waves.py
wmsan/subfunctions_rayleigh_waves.py
wmsan/synthetics.py
wmsan/temporal_variation.py
wmsan/wmsan_to_noisi.py
wmsan-2025.0.0.dist-info/METADATA
wmsan-2025.0.0.dist-info/WHEEL
wmsan-2025.0.0.dist-info/licenses/LICENSE
wmsan-2025.0.0.dist-info/RECORD
