Metadata-Version: 2.3
Name: wmsan
Version: 2025.0.0
Summary: Compute seismic sources of ambient noise using wave model hindcast outputs.
Project-URL: Homepage, https://gricad-gitlab.univ-grenoble-alpes.fr/tomasetl/ww3-source-maps/
Project-URL: Issues, https://gricad-gitlab.univ-grenoble-alpes.fr/tomasetl/ww3-source-maps/-/issues
Project-URL: Documentation, https://tomasetl.gricad-pages.univ-grenoble-alpes.fr/ww3-source-maps/
Author-email: Lisa Tomasetto <lisa.tomasetto@gmail.com>
Classifier: License :: OSI Approved :: MIT License
Classifier: Operating System :: MacOS
Classifier: Operating System :: Unix
Classifier: Programming Language :: Python :: 3
Requires-Python: <3.13
Requires-Dist: cartopy
Requires-Dist: dask
Requires-Dist: datetime
Requires-Dist: h5py
Requires-Dist: ipykernel
Requires-Dist: matplotlib
Requires-Dist: netcdf4
Requires-Dist: notebook
Requires-Dist: numpy<2.0.0
Requires-Dist: obspy
Requires-Dist: pandas
Requires-Dist: pyproj
Requires-Dist: scipy
Requires-Dist: tqdm
Requires-Dist: xarray
